LICENSE.txt
README.md
setup.cfg
setup.py
susscanner/__init__.py
susscanner/__main__.py
susscanner/cli.py
susscanner/config.py
susscanner/rules_metadata.json
susscanner/scan.py
susscanner/rules/api_gw.guard
susscanner/rules/cloud_front.guard
susscanner/rules/cloudwatch.guard
susscanner/rules/codeguru.guard
susscanner/rules/ec2.guard
susscanner/rules/emr.guard
susscanner/rules/glue.guard
susscanner/rules/graviton.guard
susscanner/rules/rds.guard
susscanner/rules/s3.guard
susscanner/rules/test_cases/api_gw_tests.yaml
susscanner/rules/test_cases/cloud_front_tests.yaml
susscanner/rules/test_cases/cloudwatch_tests.yaml
susscanner/rules/test_cases/codeguru_tests.yaml
susscanner/rules/test_cases/ec2_tests.yaml
susscanner/rules/test_cases/emr_tests.yaml
susscanner/rules/test_cases/glue_tests.yaml
susscanner/rules/test_cases/graviton_tests.yaml
susscanner/rules/test_cases/rds_tests.yaml
susscanner/rules/test_cases/s3_tests.yaml
sustainability_scanner.egg-info/PKG-INFO
sustainability_scanner.egg-info/SOURCES.txt
sustainability_scanner.egg-info/dependency_links.txt
sustainability_scanner.egg-info/entry_points.txt
sustainability_scanner.egg-info/requires.txt
sustainability_scanner.egg-info/top_level.txt
tests/test_scan.py