Metadata-Version: 2.1
Name: sustainability-scanner
Version: 1.3.0
Summary: Sustainability Scanner
Home-page: http://github.com/awslabs/sustainability-scanner
Author: AWS
License: MIT-0
Classifier: Development Status :: 4 - Beta
Classifier: Intended Audience :: Developers
Classifier: Intended Audience :: System Administrators
Classifier: Natural Language :: English
Classifier: License :: OSI Approved :: MIT No Attribution License (MIT-0)
Classifier: Programming Language :: Python
Classifier: Programming Language :: Python :: 3
Requires-Python: >=3.6
License-File: LICENSE.txt
